slack_forms/__init__.py
slack_forms/forms/__init__.py
slack_forms/forms/blocks.py
slack_forms/forms/exceptions.py
slack_forms/forms/fields.py
slack_forms/forms/forms.py
slack_forms/logging/__init__.py
slack_forms/logging/logging.py
slack_forms/views/__init__.py
slack_forms/views/views.py
slack_forms-0.3.0.dist-info/LICENSE
slack_forms-0.3.0.dist-info/METADATA
slack_forms-0.3.0.dist-info/WHEEL
slack_forms-0.3.0.dist-info/top_level.txt
slack_forms-0.3.0.dist-info/RECORD
